physicsLab/__init__.py
physicsLab/_colorUtils.py
physicsLab/_core.py
physicsLab/_tools.py
physicsLab/_typing.py
physicsLab/_unwind.py
physicsLab/_warn.py
physicsLab/chart.py
physicsLab/element.py
physicsLab/enums.py
physicsLab/errors.py
physicsLab/physicsLab_version.py
physicsLab/plAR.py
physicsLab/savTemplate.py
physicsLab/utils.py
physicsLab/celestial/__init__.py
physicsLab/celestial/_planetbase.py
physicsLab/celestial/planets.py
physicsLab/circuit/__init__.py
physicsLab/circuit/_circuit_core.py
physicsLab/circuit/elements/__init__.py
physicsLab/circuit/elements/artificialCircuit.py
physicsLab/circuit/elements/basicCircuit.py
physicsLab/circuit/elements/logicCircuit.py
physicsLab/circuit/elements/otherCircuit.py
physicsLab/circuit/elements/sensor.py
physicsLab/electromagnetism/__init__.py
physicsLab/electromagnetism/_electromagnetismBase.py
physicsLab/electromagnetism/elements.py
physicsLab/lib/__init__.py
physicsLab/lib/analog_circuit/__init__.py
physicsLab/lib/analog_circuit/analog.py
physicsLab/lib/logic_circuit/__init__.py
physicsLab/lib/logic_circuit/edge_trigger.py
physicsLab/lib/logic_circuit/logic.py
physicsLab/lib/logic_circuit/super_logic_gate.py
physicsLab/lib/logic_circuit/wires.py
physicsLab/music/__init__.py
physicsLab/music/music.py
physicsLab/music/mido/__init__.py
physicsLab/music/mido/frozen.py
physicsLab/music/mido/parser.py
physicsLab/music/mido/ports.py
physicsLab/music/mido/sockets.py
physicsLab/music/mido/syx.py
physicsLab/music/mido/tokenizer.py
physicsLab/music/mido/messages/__init__.py
physicsLab/music/mido/messages/checks.py
physicsLab/music/mido/messages/decode.py
physicsLab/music/mido/messages/encode.py
physicsLab/music/mido/messages/messages.py
physicsLab/music/mido/messages/specs.py
physicsLab/music/mido/messages/strings.py
physicsLab/music/mido/midifiles/__init__.py
physicsLab/music/mido/midifiles/meta.py
physicsLab/music/mido/midifiles/midifiles.py
physicsLab/music/mido/midifiles/tracks.py
physicsLab/music/mido/midifiles/units.py
physicslab-2.0.5.dist-info/licenses/LICENSE
physicslab-2.0.5.dist-info/METADATA
physicslab-2.0.5.dist-info/WHEEL
physicslab-2.0.5.dist-info/top_level.txt
physicslab-2.0.5.dist-info/RECORD
