Metadata-Version: 2.4
Name: physicsLab
Version: 2.0.5
Summary: Python API for Quantum-Physics App
Home-page: https://github.com/GoodenoughPhysicsLab/physicsLab
Author: Arendelle
Author-email: 2381642961@qq.com
License: MIT
Classifier: Programming Language :: Python :: 3
Classifier: License :: OSI Approved :: MIT License
Classifier: Natural Language :: Chinese (Simplified)
Classifier: Operating System :: OS Independent
Requires-Python: >=3.8
License-File: LICENSE
Requires-Dist: typing-extensions
Requires-Dist: requests==2.32.3
Requires-Dist: executing==2.2.0
Dynamic: author
Dynamic: author-email
Dynamic: classifier
Dynamic: description
Dynamic: description-content-type
Dynamic: home-page
Dynamic: license
Dynamic: license-file
Dynamic: requires-dist
Dynamic: requires-python
Dynamic: summary
